config_source_s3.py
config_source_s3-0.1.0.dist-info/LICENSE
config_source_s3-0.1.0.dist-info/METADATA
config_source_s3-0.1.0.dist-info/WHEEL
config_source_s3-0.1.0.dist-info/entry_points.txt
config_source_s3-0.1.0.dist-info/top_level.txt
config_source_s3-0.1.0.dist-info/RECORD
